disp/__init__.py
disp/spark.py
sparklier/__init__.py
sparklier/spark.py
sparklier-0.0.2.dist-info/DESCRIPTION.rst
sparklier-0.0.2.dist-info/METADATA
sparklier-0.0.2.dist-info/RECORD
sparklier-0.0.2.dist-info/WHEEL
sparklier-0.0.2.dist-info/metadata.json
sparklier-0.0.2.dist-info/top_level.txt
