Metadata-Version: 2.0
Name: sparklier
Version: 0.0.2
Summary: Providing default representations of common objects in Python land
Home-page: http://github.com/ipython/disp
Author: IPython developers
Author-email: ipython-dev@python.org
License: BSD
Platform: UNKNOWN
